ferre/__init__.py
ferre/ferre.py
ferre-1.0.0.dist-info/METADATA
ferre-1.0.0.dist-info/WHEEL
ferre-1.0.0.dist-info/top_level.txt
ferre-1.0.0.dist-info/RECORD
